pyxtern/__init__.py
pyxtern/utils.py
pyxtern/xtern.py
pyxtern-2.0.0.dist-info/DESCRIPTION.rst
pyxtern-2.0.0.dist-info/LICENSE.txt
pyxtern-2.0.0.dist-info/METADATA
pyxtern-2.0.0.dist-info/RECORD
pyxtern-2.0.0.dist-info/WHEEL
pyxtern-2.0.0.dist-info/metadata.json
pyxtern-2.0.0.dist-info/top_level.txt
