Metadata-Version: 2.0
Name: pyxtern
Version: 2.0.0
Summary: A small package to run external command lines.
Home-page: https://gitlab.com/mar.grignard/pyxtern
Author: Martin Grignard
Author-email: mar.grignard@gmail.com
License: UNKNOWN
Platform: UNKNOWN
